micropython_event_bus/__init__.py
micropython_event_bus/producer.py
micropython_event_bus/subscriber.py
micropython_event_bus-0.0.4.dist-info/LICENSE
micropython_event_bus-0.0.4.dist-info/METADATA
micropython_event_bus-0.0.4.dist-info/WHEEL
micropython_event_bus-0.0.4.dist-info/top_level.txt
micropython_event_bus-0.0.4.dist-info/RECORD
