Metadata-Version: 2.1
Name: micropython-event-bus
Version: 0.0.4
Summary: Micropython compatible producer/subscriber event bus system with optional threading.
Home-page: https://github.com/jaycosaur/micropython-event-bus
Author: Jacob Richter
Author-email: jaycorichter@gmail.com
License: UNKNOWN
Platform: UNKNOWN
Classifier: Programming Language :: Python :: 3
Classifier: License :: OSI Approved :: MIT License
Classifier: Operating System :: OS Independent
